[1,["00XoO0H6ZFkaSVFwc70RTX@6c48a","f8bCQfayxKea3sJwQ/Rr8G@6c48a"],["_textureSource"],["cc.SpriteFrame"],0,[[[{"name":"commonBtnGray","rect":{"x":0,"y":0,"width":208,"height":88},"offset":{"x":0,"y":0},"originalSize":{"width":208,"height":88},"rotated":false,"capInsets":[0,0,0,0],"packable":true}],[0],0,[0],[0],[0]],[[{"name":"commonIconClose02","rect":{"x":0,"y":0,"width":61,"height":61},"offset":{"x":0,"y":0},"originalSize":{"width":61,"height":61},"rotated":false,"capInsets":[0,0,0,0],"packable":true}],[0],0,[0],[0],[1]]]]
